{
  "project_info": {
    "project_number": "1020286118653",
    "firebase_url": "https://phisigmapialphakappa.firebaseio.com",
    "project_id": "phisigmapialphakappa",
    "storage_bucket": "phisigmapialphakappa.appspot.com"
  },
  "client": [
    {
      "client_info": {
        "mobilesdk_app_id": "1:1020286118653:android:238bbc16dfbc312f",
        "android_client_info": {
          "package_name": "com.phisigmapialphakappachapter.android"
        }
      },
      "oauth_client": [
        {
          "client_id": "1020286118653-634c7bugn1rosgqnqcu8liq09mhtp6s2.apps.googleusercontent.com",
          "client_type": 3
        }
      ],
      "api_key": [
        {
          "current_key": "AIzaSyBYRCAYdD7ERQKwMoqddnz2dxRYlenOAFU"
        }
      ],
      "services": {
        "analytics_service": {
          "status": 1
        },
        "appinvite_service": {
          "status": 1,
          "other_platform_oauth_client": []
        },
        "ads_service": {
          "status": 2
        }
      }
    }
  ],
  "configuration_version": "1"
}